{
	"ActionLayers": [
		{
			"Actions": [
				{
					"ClassType": "DialogueAction_ShowActor",
					"bWaitInput": false,
					"ActorID": 0,
					"IsLeft": true
				},
				{
					"ClassType": "DialogueAction_Talk",
					"bWaitInput": true,
					"ActorName": "None",
					"TalkString": "Dialogue_001_001",
					"TextAppearDelay": 0.10000000149011612
				},
				{
					"ClassType": "DialogueAction_Talk",
					"bWaitInput": true,
					"ActorName": "None",
					"TalkString": "Dialogue_001_002",
					"TextAppearDelay": 0.10000000149011612
				},
				{
					"ClassType": "DialogueAction_Empty",
					"bWaitInput": false
				}
			]
		},
		{
			"Actions": [
				{
					"ClassType": "DialogueAction_Empty",
					"bWaitInput": false
				},
				{
					"ClassType": "DialogueAction_Fade",
					"bWaitInput": false,
					"IsFadeOut": false
				},
				{
					"ClassType": "DialogueAction_Empty",
					"bWaitInput": false
				},
				{
					"ClassType": "DialogueAction_Empty",
					"bWaitInput": false
				}
			]
		},
		{
			"Actions": [
				{
					"ClassType": "DialogueAction_Background",
					"bWaitInput": false,
					"BackgroundID": 13,
					"IsSwitching": false
				},
				{
					"ClassType": "DialogueAction_Empty",
					"bWaitInput": false
				},
				{
					"ClassType": "DialogueAction_Background",
					"bWaitInput": false,
					"BackgroundID": 14,
					"IsSwitching": true
				},
				{
					"ClassType": "DialogueAction_Empty",
					"bWaitInput": false
				}
			]
		}
	]
}